deepreload/__init__.py
deepreload-0.3.0.dist-info/LICENSE
deepreload-0.3.0.dist-info/METADATA
deepreload-0.3.0.dist-info/WHEEL
deepreload-0.3.0.dist-info/RECORD
